GeoAPI/Geocoding.py
GeoAPI/String_Match.py
GeoAPI/__init__.py
GeoAPI/dispersion.py
GeoAPI/open_addresses.py
GeoAPI/point_validation.py
GeoAPI/preprocessing.py
GeoAPI/utils.py
GeoAPI/visualization.py
GeoAPI/word_completer.py
GeoAPI/Data/Tabela_abreviações.csv
GeoAPI/Data/__init__.py
GeoAPI/Data/_local_data.py
GeoAPI/Data/data.csv
GeoAPI/Data/data2.csv
GeoAPI/Data/data_pelias.csv
GeoAPI/Data/id29-clientes-mapeado_consolidado.csv
GeoAPI/Data/out.csv
GeoAPI/Data/relatorio.xls
terralabgeoapi-0.0.15.dist-info/AUTHORS
terralabgeoapi-0.0.15.dist-info/LICENSE
terralabgeoapi-0.0.15.dist-info/METADATA
terralabgeoapi-0.0.15.dist-info/WHEEL
terralabgeoapi-0.0.15.dist-info/top_level.txt
terralabgeoapi-0.0.15.dist-info/RECORD
